diametrics/__init__.py
diametrics/_glycemic_events_helper.py
diametrics/directory_structure.txt
diametrics/helper.py
diametrics/metrics.py
diametrics/preprocessing.py
diametrics/transform.py
diametrics/visualizations.py
diametrics-0.4.3.dist-info/LICENSE
diametrics-0.4.3.dist-info/METADATA
diametrics-0.4.3.dist-info/WHEEL
diametrics-0.4.3.dist-info/RECORD
